mush_wikis_scraper/__init__.py
mush_wikis_scraper/cli.py
mush_wikis_scraper/links.py
mush_wikis_scraper/links_fetcher.py
mush_wikis_scraper/page_reader.py
mush_wikis_scraper/scrap_wikis.py
mush_wikis_scraper-4.0.2.dist-info/METADATA
mush_wikis_scraper-4.0.2.dist-info/WHEEL
mush_wikis_scraper-4.0.2.dist-info/entry_points.txt
mush_wikis_scraper-4.0.2.dist-info/licenses/LICENSE
mush_wikis_scraper-4.0.2.dist-info/RECORD
