Metadata-Version: 2.4
Name: mush-wikis-scraper
Version: 4.0.2
Summary: Scraper for http://mushpedia.com/, http://twin.tithom.fr/mush/, https://cmnemoi.github.io/archive_aide_aux_bolets/ and QA Mush forum threads.
Project-URL: Bug Tracker, https://github.com/cmnemoi/mush_wikis_scraper/issues
Project-URL: Changelog, https://github.com/cmnemoi/mush_wikis_scraper/blob/main/CHANGELOG.md
Project-URL: Homepage, https://github.com/cmnemoi/mush_wikis_scraper
Project-URL: Repository, https://github.com/cmnemoi/mush_wikis_scraper
Author-email: Charles-Meldhine Madi Mnemoi <charlesmeldhine.madimnemoi@gmail.com>
License-Expression: MIT
License-File: LICENSE
Classifier: Development Status :: 5 - Production/Stable
Classifier: Intended Audience :: Developers
Classifier: License :: OSI Approved :: MIT License
Classifier: Operating System :: OS Independent
Classifier: Programming Language :: Python :: 3
Classifier: Programming Language :: Python :: 3.10
Classifier: Programming Language :: Python :: 3.11
Classifier: Programming Language :: Python :: 3.12
Classifier: Programming Language :: Python :: 3.13
Requires-Python: <3.14,>=3.10
Requires-Dist: beautifulsoup4>=4.14.3
Requires-Dist: httpx>=0.28.1
Requires-Dist: markdownify>=1.2.2
Requires-Dist: tqdm>=4.67.1
Requires-Dist: trafilatura[all]>=2.0.0
Requires-Dist: typer>=0.21.1
